rio_trend/__init__.py
rio_trend/operations.py
rio_trend/utils.py
rio_trend/workers.py
rio_trend/scripts/__init__.py
rio_trend/scripts/cli.py
rio_trend-1.2.1.dist-info/METADATA
rio_trend-1.2.1.dist-info/WHEEL
rio_trend-1.2.1.dist-info/entry_points.txt
rio_trend-1.2.1.dist-info/top_level.txt
rio_trend-1.2.1.dist-info/RECORD
