Metadata-Version: 2.1
Name: rio-trend
Version: 1.2.1
Home-page: 
Author: 
Author-email: 
License: BSD
Classifier: Topic :: Scientific/Engineering :: GIS
Requires-Dist: pymannkendall
Requires-Dist: click (>=4.0)
Requires-Dist: rasterio (~=1.0)
Requires-Dist: rio-mucho
Requires-Dist: enum34 ; python_version < "3.4"
